LICENSE.txt
MANIFEST.in
README.rst
setup.cfg
setup.py
versioneer.py
bin/splaunch
splauncher/__init__.py
splauncher/_version.py
splauncher/core.py
splauncher.egg-info/PKG-INFO
splauncher.egg-info/SOURCES.txt
splauncher.egg-info/dependency_links.txt
splauncher.egg-info/top_level.txt
splauncher.egg-info/zip-safe