Metadata-Version: 1.1
Name: splauncher
Version: 0.0.10
Summary: A simple subprocess launcher with optional DRMAA support.
Home-page: https://github.com/jakirkham/splauncher
Author: John Kirkham
Author-email: kirkhamj@janelia.hhmi.org
License: BSD 3-Clause
Keywords: splauncher
Platform: UNKNOWN
Classifier: Development Status :: 2 - Pre-Alpha
Classifier: Intended Audience :: Developers
Classifier: License :: OSI Approved :: BSD License
Classifier: Natural Language :: English
Classifier: Programming Language :: Python :: 2
Classifier: Programming Language :: Python :: 2.7
Classifier: Programming Language :: Python :: 3
Classifier: Programming Language :: Python :: 3.4
Classifier: Programming Language :: Python :: 3.5
Classifier: Programming Language :: Python :: 3.6
